ingredients_http/__init__.py
ingredients_http/app.py
ingredients_http/app_mount.py
ingredients_http/request_methods.py
ingredients_http/route.py
ingredients_http/router.py
ingredients_http/errors/__init__.py
ingredients_http/errors/validation.py
ingredients_http/test/__init__.py
ingredients_http/test/base.py
ingredients_http/test/test_application.py
ingredients_http/test/test_router.py
ingredients_http/test/routes/__init__.py
ingredients_http/test/routes/app/__init__.py
ingredients_http/test/routes/app/bar.py
ingredients_http/test/routes/app/baz.py
ingredients_http/test/routes/app/foo.py
ingredients_http/test/routes/app/qux.py
ingredients_http/test/routes/app/validation_models/__init__.py
ingredients_http/test/routes/app/validation_models/bar.py
ingredients_http/test/routes/app/validation_models/baz.py
ingredients_http/test/routes/app/validation_models/foo.py
ingredients_http/test/routes/app/validation_models/qux.py
ingredients_http/test/routes/none/__init__.py
ingredients_http/test/routes/with/__init__.py
ingredients_http/test/routes/with/foo.py
ingredients_http/tools/__init__.py
ingredients_http/tools/model.py
ingredients_http/tools/param_validation.py
ingredients.http-0.0.23.dist-info/LICENSE
ingredients.http-0.0.23.dist-info/METADATA
ingredients.http-0.0.23.dist-info/WHEEL
ingredients.http-0.0.23.dist-info/pbr.json
ingredients.http-0.0.23.dist-info/top_level.txt
ingredients.http-0.0.23.dist-info/RECORD
