Metadata-Version: 2.1
Name: ingredients.http
Version: 0.0.23
Summary: HTTP Library for RESTful APIs
Home-page: https://github.com/rmb938/ingredients.http
Author: Ryan Belgrave
Author-email: rmb1993@gmail.com
License: MIT
Platform: UNKNOWN
Classifier: Development Status :: 3 - Alpha
Classifier: Environment :: Web Environment
Classifier: Intended Audience :: Developers
Classifier: License :: OSI Approved :: MIT License
Classifier: Operating System :: OS Independent
Classifier: Programming Language :: Python
Classifier: Topic :: Internet :: WWW/HTTP
Classifier: Topic :: Software Development :: Libraries :: Application Frameworks
Requires-Dist: cherrypy (>=18.0.1)
Requires-Dist: Routes (>=2.4.1)
Requires-Dist: schematics (>=2.0.1)
Requires-Dist: arrow (>=0.10.0)
